tac/__init__.py
tac/date_cleaner.py
tidy_archive_catalogues-0.0.1.dist-info/METADATA
tidy_archive_catalogues-0.0.1.dist-info/WHEEL
tidy_archive_catalogues-0.0.1.dist-info/top_level.txt
tidy_archive_catalogues-0.0.1.dist-info/RECORD
