Metadata-Version: 2.1
Name: tidy-archive-catalogues
Version: 0.0.1
Summary: Code to tidy archivist catalogues into human- and computer-readable formats.
Home-page: https://github.com/NatalieThurlby/tidy-archive-catalogues
Author: Natalie Thurlby
Author-email: natalie.thurlby@bristol.ac.uk
License: UNKNOWN
Platform: UNKNOWN
Classifier: Programming Language :: Python :: 3
Classifier: License :: OSI Approved :: MIT License
Classifier: Operating System :: OS Independent
Requires-Python: >=3.6
